heic_to_jpg/__init__.py
heic_to_jpg/cli.py
heic_to_jpg-0.2.0.dist-info/LICENSE
heic_to_jpg-0.2.0.dist-info/METADATA
heic_to_jpg-0.2.0.dist-info/WHEEL
heic_to_jpg-0.2.0.dist-info/entry_points.txt
heic_to_jpg-0.2.0.dist-info/top_level.txt
heic_to_jpg-0.2.0.dist-info/RECORD
