Metadata-Version: 2.1
Name: heic_to_jpg
Version: 0.2.0
Summary: Convert .heic images to .jpg
Home-page: https://github.com/creimers/heic-to-jpg
Author: Christoph Reimers
Author-email: christoph@superservice-international.com
License: MIT license
Keywords: heic_to_jpg
Classifier: Development Status :: 2 - Pre-Alpha
Classifier: Intended Audience :: Developers
Classifier: License :: OSI Approved :: MIT License
Classifier: Natural Language :: English
Classifier: Programming Language :: Python :: 3
Classifier: Programming Language :: Python :: 3.5
Classifier: Programming Language :: Python :: 3.6
Classifier: Programming Language :: Python :: 3.7
Classifier: Programming Language :: Python :: 3.8
Requires-Python: >=3.5
License-File: LICENSE
Requires-Dist: Click>=7.0
